{
  "title": "Sample Hotel",
  "description": "A beautiful hotel",
  "guestCount": 4,
  "bedroomCount": 2,
  "bathroomCount": 2,
  "amenities": [
    "wifi",
    "parking"
  ],
  "host": {
    "name": "John Doe",
    "email": "john@example.com",
    "phone": "123-456-7890"
  },
  "address": {
    "street": "123 Main St",
    "city": "Sample City",
    "state": "Sample State",
    "country": "Sample Country",
    "zipCode": "12345"
  },
  "location": {
    "latitude": 12.34,
    "longitude": 56.78
  },
  "id": "1731414488981",
  "slug": "sample-hotel",
  "images": [
    "/uploads/images/1731415817614.jpg",
    "/uploads/images/1731415817617.jpg",
    "/uploads/images/1731415817620.jpg",
    "/uploads/images/1731415817621.jpg"
  ],
  "rooms": [
    {
      "roomTitle": "Deluxe Suite",
      "bedroomCount": 1,
      "hotelSlug": "sample-hotel",
      "roomSlug": "deluxe-suite",
      "roomImage": "/uploads/images/1731415369042.jpg"
    }
  ]
}